raincloudy/__init__.py
raincloudy/const.py
raincloudy/controller.py
raincloudy/core.py
raincloudy/exceptions.py
raincloudy/faucet.py
raincloudy/helpers.py
raincloudy/wifiaquatimer_com_chain.cer
raincloudy/aio/__init__.py
raincloudy/aio/controller.py
raincloudy/aio/core.py
raincloudy/aio/faucet.py
raincloudy-1.2.0.dist-info/LICENSE
raincloudy-1.2.0.dist-info/METADATA
raincloudy-1.2.0.dist-info/WHEEL
raincloudy-1.2.0.dist-info/top_level.txt
raincloudy-1.2.0.dist-info/RECORD
