Metadata-Version: 2.1
Name: raincloudy
Version: 1.2.0
Summary: A Python library to communicate with Melnor                  RainCloud Smart Garden Watering Irrigation Timer                  (https://wwww.melnor.com/)
Home-page: https://github.com/tchellomello/raincloudy
Author: Marcelo Moreira de Mello
Author-email: tchello.mello@gmail.com
License: Apache License 2.0
Keywords: garden,irrigation,melnor,rain cloud,water
License-File: LICENSE
Requires-Dist: requests (>=2.0)
Requires-Dist: bs4
Requires-Dist: urllib3 (>=1.22)
Requires-Dist: html5lib (==1.1)
